MANIFEST.in
setup.py
bin/elastic
lmpIndentation/__init__.py
lmpIndentation/indentation.py
lmpIndentation/plotfigure.py
lmpIndentation.egg-info/PKG-INFO
lmpIndentation.egg-info/SOURCES.txt
lmpIndentation.egg-info/dependency_links.txt
lmpIndentation.egg-info/not-zip-safe
lmpIndentation.egg-info/requires.txt
lmpIndentation.egg-info/top_level.txt
lmpIndentation/templates/elastic/displace.mod
lmpIndentation/templates/elastic/in.elastic
lmpIndentation/templates/elastic/in.elastic.template
lmpIndentation/templates/elastic/init.mod
lmpIndentation/templates/elastic/potential.mod