Metadata-Version: 1.0
Name: lmpIndentation
Version: 0.5
Summary: Useful package for processing indentation data
Home-page: UNKNOWN
Author: Linyuan Shi
Author-email: Linyuan.shi@outlook.com
License: MIT
Platform: UNKNOWN
